feishu_logging/__init__.py
feishu_logging/handler.py
feishu_logging/handler_test.py
test/__init__.py
test/test copy.py
test/test.py
feishu_logging_handler-1.0.8.dist-info/LICENSE
feishu_logging_handler-1.0.8.dist-info/METADATA
feishu_logging_handler-1.0.8.dist-info/WHEEL
feishu_logging_handler-1.0.8.dist-info/top_level.txt
feishu_logging_handler-1.0.8.dist-info/RECORD
