Metadata-Version: 2.1
Name: feishu_logging_handler
Version: 1.0.8
Summary: logging的飞书handler
Home-page: https://github.com/smockgithub/feishu-logging-handler
Author: smock
Author-email: smockg@gmail.com
Classifier: Programming Language :: Python :: 3
Classifier: License :: OSI Approved :: MIT License
Classifier: Operating System :: OS Independent
Requires-Python: >=3
License-File: LICENSE
Requires-Dist: httpx
Requires-Dist: cachetools
